lib_clds/__init__.py
lib_clds-0.1.dist-info/METADATA
lib_clds-0.1.dist-info/WHEEL
lib_clds-0.1.dist-info/top_level.txt
lib_clds-0.1.dist-info/RECORD
